Aliyah/__init__.py
Aliyah/predictors.py
aliyah_predictor-0.1.2.dist-info/METADATA
aliyah_predictor-0.1.2.dist-info/WHEEL
aliyah_predictor-0.1.2.dist-info/top_level.txt
aliyah_predictor-0.1.2.dist-info/RECORD
